django_assert_queries/__init__.py
django_assert_queries/_version.py
django_assert_queries/py.typed
django_assert_queries/query_catcher.py
django_assert_queries/query_comparator.py
django_assert_queries/testing.py
django_assert_queries/tests/__init__.py
django_assert_queries/tests/models.py
django_assert_queries/tests/test_query_catcher.py
django_assert_queries/tests/test_query_comparator.py
django_assert_queries-2.0.1.dist-info/METADATA
django_assert_queries-2.0.1.dist-info/WHEEL
django_assert_queries-2.0.1.dist-info/top_level.txt
django_assert_queries-2.0.1.dist-info/RECORD
