Metadata-Version: 2.4
Name: django-assert-queries
Version: 2.0.1
Summary: Assert and instrument executed database queries using Django.
Author-email: "Beanbag, Inc." <questions@beanbaginc.com>
License: MIT
Project-URL: Homepage, https://github.com/beanbaginc/django-assert-queries
Project-URL: Documentation, https://github.com/beanbaginc/django-assert-queries
Project-URL: Repository, https://github.com/beanbaginc/django-assert-queries
Keywords: database,django,pytest,sql,unit tests
Classifier: Development Status :: 5 - Production/Stable
Classifier: Environment :: Other Environment
Classifier: Framework :: Pytest
Classifier: Intended Audience :: Developers
Classifier: License :: OSI Approved :: MIT License
Classifier: Operating System :: OS Independent
Classifier: Programming Language :: Python
Classifier: Programming Language :: Python :: 3
Classifier: Programming Language :: Python :: 3.8
Classifier: Programming Language :: Python :: 3.9
Classifier: Programming Language :: Python :: 3.10
Classifier: Programming Language :: Python :: 3.11
Classifier: Programming Language :: Python :: 3.12
Classifier: Programming Language :: Python :: 3.13
Classifier: Topic :: Software Development
Classifier: Topic :: Software Development :: Libraries
Classifier: Topic :: Software Development :: Libraries :: Python Modules
Classifier: Topic :: Software Development :: Testing
Requires-Python: >=3.8
Requires-Dist: kgb>=7.1.1
Requires-Dist: typing_extensions>=4.4
